scviz/__init__.py
scviz/pAnnData.py
scviz/plotting.py
scviz/setup.py
scviz/utils.py
scviz-0.1.10.dist-info/LICENSE
scviz-0.1.10.dist-info/METADATA
scviz-0.1.10.dist-info/WHEEL
scviz-0.1.10.dist-info/top_level.txt
scviz-0.1.10.dist-info/RECORD
