Metadata-Version: 2.1
Name: scviz
Version: 0.1.10
Summary: A package to visualize single cell proteomics (and more to come!) data
Author-email: Marion Pang <sr_pang@hotmail.com>
Project-URL: Homepage, https://github.com/gnaprs/scviz
Project-URL: Issues, https://github.com/gnaprs/scviz/issues
Classifier: Programming Language :: Python :: 3
Classifier: License :: OSI Approved :: MIT License
Classifier: Development Status :: 3 - Alpha
Classifier: Operating System :: OS Independent
Requires-Python: >=3.8
License-File: LICENSE
Requires-Dist: numpy ==1.26.4
Requires-Dist: pandas ==2.2.2
Requires-Dist: matplotlib ==3.8.4
Requires-Dist: seaborn ==0.13.2
Requires-Dist: upsetplot ==0.9.0
Requires-Dist: scikit-learn ==1.4.2
Requires-Dist: scipy ==1.13.0
Requires-Dist: umap-learn ==0.5.6
Requires-Dist: adjustText ==1.1.1
Requires-Dist: anndata ==0.10.7
Requires-Dist: requests
Requires-Dist: matplotlib-venn ==0.11.10
Requires-Dist: pyarrow
Requires-Dist: scanpy
Provides-Extra: pytest
Requires-Dist: openpyxl ; extra == 'pytest'
